docusign_integration/__init__.py
docusign_integration/api/__init__.py
docusign_integration/api/auth.py
docusign_integration/api/envelope.py
docusign_integration/models/__init__.py
docusign_integration/models/auth.py
docusign_integration/models/envelope.py
docusign_integration-1.1.0.dist-info/WHEEL
docusign_integration-1.1.0.dist-info/METADATA
docusign_integration-1.1.0.dist-info/RECORD
