Metadata-Version: 2.1
Name: docusign-integration
Version: 1.1.0
Summary: 
Author: nichmorgan-loft
Author-email: nich.morgan@loft.com.br
Requires-Python: >=3.8,<4.0
Classifier: Programming Language :: Python :: 3
Classifier: Programming Language :: Python :: 3.8
Classifier: Programming Language :: Python :: 3.9
Requires-Dist: PyMuPDF (>=1.18.19,<2.0.0)
Requires-Dist: pydantic (>=1.8.2,<2.0.0)
Requires-Dist: pydash (>=5.0.2,<6.0.0)
Requires-Dist: requests (>=2.26.0,<3.0.0)
Requires-Dist: requests-oauthlib (>=1.3.0,<2.0.0)
